sgGWR/__init__.py
sgGWR/kernels.py
sgGWR/models.py
sgGWR/optimizers/__init__.py
sgGWR/optimizers/existings.py
sgGWR/optimizers/existings_numpy.py
sgGWR/optimizers/golden.py
sgGWR/optimizers/second.py
sgGWR/optimizers/sg.py
sgGWR/optimizers/sg_numpy.py
sgGWR/optimizers/vr.py
sggwr-0.1.5.dist-info/licenses/LICENSE
sggwr-0.1.5.dist-info/METADATA
sggwr-0.1.5.dist-info/WHEEL
sggwr-0.1.5.dist-info/top_level.txt
sggwr-0.1.5.dist-info/RECORD
